container_hub/__init__.py
container_hub/exceptions.py
container_hub/models.py
container_hub/version.py
container_hub/carriers/__init__.py
container_hub/carriers/docker/__init__.py
container_hub/carriers/docker/backend.py
container_hub/carriers/docker/tests/__init__.py
container_hub/carriers/docker/tests/test_docker_backend.py
container_hub/carriers/kubernetes/__init__.py
container_hub/carriers/kubernetes/backend.py
container_hub/carriers/kubernetes/tests/__init__.py
container_hub/carriers/kubernetes/tests/test_kubernetes_backend.py
container_hub-0.1.21.dist-info/AUTHORS.rst
container_hub-0.1.21.dist-info/LICENSE
container_hub-0.1.21.dist-info/METADATA
container_hub-0.1.21.dist-info/WHEEL
container_hub-0.1.21.dist-info/top_level.txt
container_hub-0.1.21.dist-info/RECORD
