Metadata-Version: 2.1
Name: container_hub
Version: 0.1.21
Summary: The 3Di simulation container hub
Home-page: https://github.com/nens/container-hub
Author: Lars Claussen
Author-email: claussen.lars@nelen-schuurmans.nl
License: MIT license
Keywords: container_hub
Classifier: Development Status :: 2 - Pre-Alpha
Classifier: Intended Audience :: Developers
Classifier: License :: OSI Approved :: MIT License
Classifier: Natural Language :: English
Classifier: Programming Language :: Python :: 3.8
License-File: LICENSE
License-File: AUTHORS.rst
Requires-Dist: docker
Requires-Dist: python-slugify
Requires-Dist: kubernetes
Requires-Dist: hikaru>=1.0
